apifactory/__init__.py
apifactory/app_factory.py
apifactory/database.py
apifactory/route_factory.py
apifactory/router_methods.py
apifactory/schemas.py
apifactory/security.py
apifactory/utils.py
apifactory-0.6.0.dist-info/WHEEL
apifactory-0.6.0.dist-info/METADATA
apifactory-0.6.0.dist-info/RECORD
