Metadata-Version: 2.1
Name: apifactory
Version: 0.6.0
Summary: package for automatically creating an api on an existing database
Home-page: https://apifactory.readthedocs.io/en/latest/index.html
License: MIT
Keywords: API,automatic
Author: Sebastiaan Broekema
Author-email: sebastiaanbroekema@gmail.com
Requires-Python: >=3.9,<3.10
Classifier: Development Status :: 3 - Alpha
Classifier: License :: OSI Approved :: MIT License
Classifier: Programming Language :: Python :: 3
Classifier: Programming Language :: Python :: 3.9
Classifier: Topic :: Internet
Provides-Extra: mssql
Requires-Dist: PyYAML (>=5.0.0,<6.0.0)
Requires-Dist: bcrypt (>=3.0.0,<4.0.0)
Requires-Dist: fastapi (<1.0.0)
Requires-Dist: fastapi-pagination (>=0.8.3,<0.9.0)
Requires-Dist: passlib (>=1.0.0,<2.0.0)
Requires-Dist: pydantic (>=1.0.0,<2.0.0)
Requires-Dist: pydantic-sqlalchemy (<1.0.0)
Requires-Dist: pymssql (>=2.0.0,<3.0.0); extra == "mssql"
Requires-Dist: python-jose (>=3.0.0,<4.0.0)
Requires-Dist: python-multipart (<1.0.0)
Requires-Dist: slowapi (>=0.1.5,<0.2.0)
Requires-Dist: sqlalchemy (>=1.0.0,<2.0.0)
Requires-Dist: uvicorn (<1.0.0)
Project-URL: Repository, https://github.com/sebastiaanbroekema/apifactory
